origen_autoapi/__init__.py
origen_autoapi/apinode.py
origen_autoapi/sphinx.py
origen_autoapi/templates/autoapi/module.rst
origen_autoapi-2.0.1.dist-info/LICENSE
origen_autoapi-2.0.1.dist-info/METADATA
origen_autoapi-2.0.1.dist-info/WHEEL
origen_autoapi-2.0.1.dist-info/top_level.txt
origen_autoapi-2.0.1.dist-info/RECORD
