Metadata-Version: 2.1
Name: origen-autoapi
Version: 2.0.1
Summary: Automatic API reference documentation generation for Sphinx inspired by Doxygen, with changes for the Origen project.
Home-page: https://origen_autoapi.readthedocs.org/
Author: KuraLabs S.R.L, Origen-SDK
License: UNKNOWN
Keywords: autoapi,origen
Platform: UNKNOWN
Classifier: Development Status :: 5 - Production/Stable
Classifier: Intended Audience :: Developers
Classifier: License :: OSI Approved :: Apache Software License
Classifier: Natural Language :: English
Classifier: Operating System :: POSIX :: Linux
Classifier: Programming Language :: Python :: 3
Classifier: Programming Language :: Python :: 3.4
Classifier: Programming Language :: Python :: 3.5
Classifier: Programming Language :: Python :: 3.6
Requires-Dist: sphinx
